allbaro/__init__.py
allbaro/base.py
allbaro/errors.py
allbaro/helpers/__init__.py
allbaro/helpers/headers.py
allbaro/helpers/keys.py
tests/__init__.py
allbaro_chunilpathfinder-0.0.1.dist-info/LICENSE
allbaro_chunilpathfinder-0.0.1.dist-info/METADATA
allbaro_chunilpathfinder-0.0.1.dist-info/WHEEL
allbaro_chunilpathfinder-0.0.1.dist-info/top_level.txt
allbaro_chunilpathfinder-0.0.1.dist-info/RECORD
