Metadata-Version: 2.1
Name: allbaro-chunilpathfinder
Version: 0.0.1
Summary: 한국환경공단 올바로 시스템 스크래핑을 위한 파이썬 라이브러리
Home-page: https://github.com/chunil-energy/allbaro
Author: cuhong
Author-email: hongcoilhouse@gmail.com
Classifier: Programming Language :: Python :: 3
Classifier: License :: OSI Approved :: MIT License
Classifier: Operating System :: OS Independent
Requires-Python: >=3.9
License-File: LICENSE
